[
	{
		"__TYPE__": "SharedSliceContent",
		"variation": "default",
		"primary": {
			"content": {
				"__TYPE__": "StructuredTextContent",
				"value": [
					{
						"type": "paragraph",
						"content": {
							"text": "Commodo aliqua reprehenderit tempor et reprehenderit sunt sit commodo velit ut veniam consectetur exercitation esse. Do aliquip ut do est amet. Incididunt id nisi anim consequat est in reprehenderit magna et."
						}
					}
				]
			}
		},
		"items": [
			{
				"__TYPE__": "GroupItemContent",
				"value": []
			}
		]
	}
]